LICENSE
README.md
setup.py
PLTable.egg-info/PKG-INFO
PLTable.egg-info/SOURCES.txt
PLTable.egg-info/dependency_links.txt
PLTable.egg-info/top_level.txt
pltable/__init__.py
pltable/compat.py
pltable/factory.py
pltable/pltable.py