Metadata-Version: 2.1
Name: PLTable
Version: 1.1.0
Summary: Python 3 library for easily displaying tabular data in a visually appealing text table format
Home-page: https://github.com/platomav/PLTable
Author: Luke Maurits, Kane Blueriver, Ryan James, Plato Mavropoulos
Maintainer: Plato Mavropoulos
License: BSD (3 clause)
Classifier: Programming Language :: Python :: 3
Classifier: License :: OSI Approved :: BSD License
Classifier: Operating System :: OS Independent
Classifier: Topic :: Text Processing
License-File: LICENSE
